ca_visionlearn/__init__.py
ca_visionlearn/color_utils.py
ca_visionlearn/metrics.py
ca_visionlearn/product_color_processor.py
ca_visionlearn/skin_tone_extraction.py
ca_visionlearn-3.3.dist-info/METADATA
ca_visionlearn-3.3.dist-info/WHEEL
ca_visionlearn-3.3.dist-info/top_level.txt
ca_visionlearn-3.3.dist-info/RECORD
